actionweaver/__init__.py
actionweaver/actions/__init__.py
actionweaver/actions/action.py
actionweaver/actions/factories/__init__.py
actionweaver/actions/factories/combine.py
actionweaver/actions/factories/function.py
actionweaver/actions/factories/instructor.py
actionweaver/actions/factories/langchain.py
actionweaver/actions/factories/pydantic_model_to_action.py
actionweaver/actions/factories/repeat.py
actionweaver/llms/__init__.py
actionweaver/llms/azure/__init__.py
actionweaver/llms/azure/chat.py
actionweaver/llms/azure/chat_loop.py
actionweaver/llms/azure/functions.py
actionweaver/llms/exception_handler.py
actionweaver/llms/general/__init__.py
actionweaver/llms/general/action_processor.py
actionweaver/llms/general/chat.py
actionweaver/llms/general/tools.py
actionweaver/llms/loop_action.py
actionweaver/llms/openai/functions/__init__.py
actionweaver/llms/openai/functions/chat.py
actionweaver/llms/openai/functions/functions.py
actionweaver/llms/openai/tools/__init__.py
actionweaver/llms/openai/tools/chat.py
actionweaver/llms/openai/tools/chat_loop.py
actionweaver/llms/openai/tools/tools.py
actionweaver/llms/patch.py
actionweaver/llms/wrapper.py
actionweaver/mixins/__init__.py
actionweaver/mixins/examples/__init__.py
actionweaver/mixins/examples/folium.py
actionweaver/mixins/examples/langchain.py
actionweaver/mixins/examples/openai.py
actionweaver/telemetry/__init__.py
actionweaver/telemetry/helpers.py
actionweaver/utils/__init__.py
actionweaver/utils/action_scope.py
actionweaver/utils/cache.py
actionweaver/utils/output.py
actionweaver/utils/pydantic_utils.py
actionweaver/utils/stream.py
actionweaver/utils/tokens.py
actionweaver-0.0.32.dist-info/LICENSE
actionweaver-0.0.32.dist-info/METADATA
actionweaver-0.0.32.dist-info/WHEEL
actionweaver-0.0.32.dist-info/RECORD
