Metadata-Version: 2.1
Name: actionweaver
Version: 0.0.32
Summary: An Application Framework for Building LLM Agents
Author: Teng "Niel" Hu
Author-email: hu.niel92@gmail.com
Requires-Python: >=3.9,<4.0
Classifier: Programming Language :: Python :: 3
Classifier: Programming Language :: Python :: 3.9
Classifier: Programming Language :: Python :: 3.10
Classifier: Programming Language :: Python :: 3.11
Classifier: Programming Language :: Python :: 3.12
Requires-Dist: openai (>=1.5.0,<2.0.0)
Requires-Dist: pydantic (>=2.5.2,<3.0.0)
